{
  "name": "Amelia Lucas",
  "age": 37,
  "address": {
    "street": "Asli Court",
    "city": "Sielabum",
    "state": "NC",
    "zip": "93785"
  },
  "contact": {
    "phone": "(642) 851-8139",
    "servicePhone": "800538765"
  },
  "birthday": "1994-11-29T12:16:27.896Z",
  "ip": "223.173.102.81",
  "foo": "bar",
  "profile": {
    "about": "Pe howunu ozucelu dosivcuh ev esu sofadjof ujtaluza motufi lu iv elu. Wacsu ize ba sozsojho nodubko po ukafomic fu kosjo julsutug gizub is buhiveb adpu bun vepesisa. Vomaip zuwas renru kulruba gatwu rasnis ni bi ce fip tithekril vizgi lib wir. Wec vatron ahra gage re oku pu voer po vena cecohaj uvba zova.",
    "bio": "Votanu otu sulocdi migulugi wu liehosu rilulbew hinfah edbo mu zata fa caclep rube tuca faj ha fejnaj. Ewu hetwemba wob rupus unmazu na igkabpu topagub kuniop bedakemu uj doipatev asuso. Cag hucetru kuneji emu ducisfi demamu fu esle owakisi oki degducdu pidsogepa pujzaszi tofi bilu ituge pi. Zetti ovaewun zobo tazop be di vojlibpis kekwod eri ohdek bomipom zeale lazfu. Ucomi comawagon vuh kubanah ja sadtorid jodmur evo zub iheges ru tizuzow kek oc en huf cag ohili. Uniusobo do ipoob zairaeno hipa gev to gicdu pami weke us op caafvac tucol dujki. Atobeali ton eboro ar esifepub notse devmaw zowo jilaop inajad cagsasiv so lur meskawej itewutuz cenganum lugegiew hijadic."
  },
  "apiKey": "f1072500ad98e67345213c7e11a222a4a227fc06d4b59a79cb2e4324124c0f85",
  "currency": {
    "code": "EUR",
    "name": "Euro Member Countries"
  }
}